[{"date":"Tue, 28 Feb 2017 03:02:05 GMT","sloc":125,"lloc":75,"functions":22,"deliveredBugs":1.067,"difficulty":29.989,"maintainability":75.841,"lintErrors":51},{"date":"Tue, 28 Feb 2017 03:02:59 GMT","sloc":125,"lloc":75,"functions":22,"deliveredBugs":1.067,"difficulty":29.989,"maintainability":75.841,"lintErrors":51},{"date":"Thu, 25 May 2017 01:40:50 GMT","sloc":125,"lloc":75,"functions":22,"deliveredBugs":1.067,"difficulty":29.989,"maintainability":75.841,"lintErrors":51},{"date":"Sat, 22 Jul 2017 21:35:16 GMT","sloc":135,"lloc":82,"functions":23,"deliveredBugs":1.204,"difficulty":35.049,"maintainability":75.1,"lintErrors":51},{"date":"Sun, 23 Jul 2017 13:55:10 GMT","sloc":135,"lloc":82,"functions":23,"deliveredBugs":1.204,"difficulty":35.049,"maintainability":75.1,"lintErrors":51},{"date":"Wed, 12 Sep 2018 15:58:37 GMT","sloc":140,"lloc":84,"functions":23,"deliveredBugs":1.304,"difficulty":34.659,"maintainability":74.53,"lintErrors":51},{"date":"Wed, 12 Sep 2018 18:28:53 GMT","sloc":142,"lloc":84,"functions":23,"deliveredBugs":1.342,"difficulty":35.045,"maintainability":74.395,"lintErrors":51},{"date":"Tue, 18 Sep 2018 15:44:04 GMT","sloc":142,"lloc":84,"functions":23,"deliveredBugs":1.342,"difficulty":35.045,"maintainability":74.395,"lintErrors":51},{"date":"Tue, 18 Sep 2018 15:49:50 GMT","sloc":142,"lloc":84,"functions":23,"deliveredBugs":1.342,"difficulty":35.045,"maintainability":74.395,"lintErrors":51}]